morefs/__init__.py
morefs/asyn_local.py
morefs/dict.py
morefs/memory.py
morefs/overlay.py
morefs/py.typed
morefs-0.2.2.dist-info/LICENSE
morefs-0.2.2.dist-info/METADATA
morefs-0.2.2.dist-info/WHEEL
morefs-0.2.2.dist-info/entry_points.txt
morefs-0.2.2.dist-info/top_level.txt
morefs-0.2.2.dist-info/RECORD
