Metadata-Version: 2.1
Name: morefs
Version: 0.2.2
Summary: A collection of self-contained fsspec-based filesystems
Author-email: Iterative <saugat@iterative.ai>
License: Apache-2.0
Project-URL: Issues, https://github.com/iterative/morefs/issues
Project-URL: Source, https://github.com/iterative/morefs
Classifier: Programming Language :: Python :: 3
Classifier: Programming Language :: Python :: 3.8
Classifier: Programming Language :: Python :: 3.9
Classifier: Programming Language :: Python :: 3.10
Classifier: Programming Language :: Python :: 3.11
Classifier: Programming Language :: Python :: 3.12
Classifier: Programming Language :: Python :: 3.13
Classifier: Development Status :: 4 - Beta
Requires-Python: >=3.8
License-File: LICENSE
Requires-Dist: fsspec
Provides-Extra: memfs
Requires-Dist: pygtrie>=2.3.2; extra == "memfs"
Provides-Extra: asynclocalfs
Requires-Dist: fsspec>=2022.10.0; extra == "asynclocalfs"
Requires-Dist: typing_extensions>=3.10.0; python_version < "3.10" and extra == "asynclocalfs"
Requires-Dist: aiofile<4,>=3.8.5; extra == "asynclocalfs"
Provides-Extra: asynclocal
Requires-Dist: morefs[asynclocalfs]; extra == "asynclocal"
Provides-Extra: all
Requires-Dist: morefs[asynclocalfs,memfs]; extra == "all"
Provides-Extra: tests
Requires-Dist: morefs[all]; extra == "tests"
Requires-Dist: pytest<9,>=7; extra == "tests"
Requires-Dist: pytest-asyncio<1,>=0.21.0; extra == "tests"
Requires-Dist: pytest-cov>=4.1.0; extra == "tests"
Requires-Dist: pytest-mock; extra == "tests"
Requires-Dist: pytest-sugar; extra == "tests"
Provides-Extra: dev
Requires-Dist: morefs[all,tests]; extra == "dev"
Requires-Dist: mypy==1.10.1; extra == "dev"
